ansible_dev_tools/__init__.py
ansible_dev_tools/__main__.py
ansible_dev_tools/_version.py
ansible_dev_tools/arg_parser.py
ansible_dev_tools/cli.py
ansible_dev_tools/server_utils.py
ansible_dev_tools/utils.py
ansible_dev_tools/version_builder.py
ansible_dev_tools/resources/server/__init__.py
ansible_dev_tools/resources/server/creator_v1.py
ansible_dev_tools/resources/server/creator_v2.py
ansible_dev_tools/resources/server/server_info.py
ansible_dev_tools/resources/server/data/__init__.py
ansible_dev_tools/resources/server/data/openapi.yaml
ansible_dev_tools/subcommands/__init__.py
ansible_dev_tools/subcommands/server.py
ansible_dev_tools-25.10.0.dist-info/licenses/LICENSE
ansible_dev_tools-25.10.0.dist-info/METADATA
ansible_dev_tools-25.10.0.dist-info/WHEEL
ansible_dev_tools-25.10.0.dist-info/entry_points.txt
ansible_dev_tools-25.10.0.dist-info/top_level.txt
ansible_dev_tools-25.10.0.dist-info/RECORD
