Metadata-Version: 2.4
Name: ansible-dev-tools
Version: 25.10.0
Summary: Ansible Developtment Tools kit bundles all tools needed for content creation and testing.
Author-email: "Bradley A. Thornton" <bthornto@redhat.com>
Maintainer-email: Ansible by Red Hat <info@ansible.com>
License-Expression: GPL-3.0-only
Project-URL: changelog, https://github.com/ansible/ansible-dev-tools/releases
Project-URL: documentation, https://ansible.readthedocs.io/projects/dev-tools/
Project-URL: homepage, https://github.com/ansible/ansible-dev-tools
Project-URL: repository, https://github.com/ansible/ansible-dev-tools
Keywords: ansible
Classifier: Development Status :: 5 - Production/Stable
Classifier: Intended Audience :: Developers
Classifier: Operating System :: OS Independent
Classifier: Programming Language :: Python
Classifier: Programming Language :: Python :: 3
Classifier: Programming Language :: Python :: 3 :: Only
Classifier: Programming Language :: Python :: 3.10
Classifier: Programming Language :: Python :: 3.11
Classifier: Programming Language :: Python :: 3.12
Classifier: Programming Language :: Python :: 3.13
Classifier: Programming Language :: Python :: Implementation :: CPython
Classifier: Topic :: Software Development
Classifier: Topic :: Utilities
Requires-Python: >=3.10
License-File: LICENSE
Requires-Dist: ansible-builder>=3.1.0
Requires-Dist: ansible-compat>=25.8.2
Requires-Dist: ansible-creator>=25.10.0
Requires-Dist: ansible-dev-environment>=25.8.0
Requires-Dist: ansible-lint>=25.9.2
Requires-Dist: ansible-navigator>=25.9.0
Requires-Dist: ansible-sign>=0.1.2
Requires-Dist: molecule>=25.9.0
Requires-Dist: pytest-ansible>=25.8.0
Requires-Dist: setuptools>=80.9.0
Requires-Dist: tox-ansible>=25.8.0
Provides-Extra: container
Requires-Dist: ansible-pylibssh==1.3.0; platform_system == "Linux" and extra == "container"
Provides-Extra: server
Requires-Dist: django<6,>=5.2.7; extra == "server"
Requires-Dist: gunicorn>=23.0.0; extra == "server"
Requires-Dist: openapi-core>=0.19.1; extra == "server"
Dynamic: license-file
